{
  "protocol_version" : "0.0.6",
  "configuration" : {
    "version" : "(6.10.0.104) (2019-12/5d03a6fe116)",
    "tlc" : "normal",
    "sigsgev" : "altstack",
    "notifications" : "kqueue",
    "architecture" : "amd64",
    "disabled_features" : "none",
    "smallconfig" : "disabled",
    "bigarrays" : "disabled",
    "softdebug" : "enabled",
    "interpreter" : "enabled",
    "llvm_support" : "0",
    "suspend" : "hybrid"
  },
  "memory" : {
    "Resident Size" : "159555584",
    "Virtual Size" : "4635201536",
    "minor_gc_time" : "262173",
    "major_gc_time" : "0",
    "minor_gc_count" : "1",
    "major_gc_count" : "0",
    "major_gc_time_concurrent" : "0"
 },
  "threads" : [
 {
    "is_managed" : true,
    "offset_free_hash" : "0x1cfb5decbf",
    "offset_rich_hash" : "0x1cfb5df079",
    "crashed" : true,
    "native_thread_id" : "0x700003d1f000",
    "thread_info_addr" : "0x7fe0b722da00",
    "thread_name" : "Thread Pool Worker",
    "ctx" : {
      "IP" : "0x7fff68be933a",
      "SP" : "0x700003d1d648",
      "BP" : "0x700003d1d670"
  },
    "managed_frames" : [
  {
      "is_managed" : "false",
      "native_address" : "unregistered"
   }
,
  {
      "is_managed" : "true",
      "guid" : "55ADAE45-46CD-485B-A70E-2948332EBE8C",
      "token" : "0x00000",
      "native_offset" : "0x0",
      "filename" : "mscorlib.dll",
      "sizeofimage" : "0x474000",
      "timestamp" : "0xcdf122ed",
      "il_offset" : "0x0000c"
   }
,
  {
      "is_managed" : "true",
      "guid" : "55ADAE45-46CD-485B-A70E-2948332EBE8C",
      "token" : "0x6001f8c",
      "native_offset" : "0x0",
      "filename" : "mscorlib.dll",
      "sizeofimage" : "0x474000",
      "timestamp" : "0xcdf122ed",
      "il_offset" : "0x0001a"
   }
,
  {
      "is_managed" : "true",
      "guid" : "55ADAE45-46CD-485B-A70E-2948332EBE8C",
      "token" : "0x6001f32",
      "native_offset" : "0x0",
      "filename" : "mscorlib.dll",
      "sizeofimage" : "0x474000",
      "timestamp" : "0xcdf122ed",
      "il_offset" : "0x00028"
   }
,
  {
      "is_managed" : "true",
      "guid" : "55ADAE45-46CD-485B-A70E-2948332EBE8C",
      "token" : "0x6001f30",
      "native_offset" : "0x0",
      "filename" : "mscorlib.dll",
      "sizeofimage" : "0x474000",
      "timestamp" : "0xcdf122ed",
      "il_offset" : "0x00002"
   }
,
  {
      "is_managed" : "true",
      "guid" : "E5BBCD86-B476-47FC-970E-F00D99CDBAB3",
      "token" : "0x6000084",
      "native_offset" : "0x0",
      "filename" : "MonoDevelop.MSBuildBuilder.exe",
      "sizeofimage" : "0x18000",
      "timestamp" : "0xc077b0d4",
      "il_offset" : "0x000ae"
   }
,
  {
      "is_managed" : "true",
      "guid" : "E5BBCD86-B476-47FC-970E-F00D99CDBAB3",
      "token" : "0x6000083",
      "native_offset" : "0x0",
      "filename" : "MonoDevelop.MSBuildBuilder.exe",
      "sizeofimage" : "0x18000",
      "timestamp" : "0xc077b0d4",
      "il_offset" : "0x00001"
   }
,
  {
      "is_managed" : "true",
      "guid" : "E5BBCD86-B476-47FC-970E-F00D99CDBAB3",
      "token" : "0x600006a",
      "native_offset" : "0x0",
      "filename" : "MonoDevelop.MSBuildBuilder.exe",
      "sizeofimage" : "0x18000",
      "timestamp" : "0xc077b0d4",
      "il_offset" : "0x00048"
   }
,
  {
      "is_managed" : "true",
      "guid" : "E5BBCD86-B476-47FC-970E-F00D99CDBAB3",
      "token" : "0x60000a1",
      "native_offset" : "0x0",
      "filename" : "MonoDevelop.MSBuildBuilder.exe",
      "sizeofimage" : "0x18000",
      "timestamp" : "0xc077b0d4",
      "il_offset" : "0x00001"
   }
,
  {
      "is_managed" : "true",
      "guid" : "E5BBCD86-B476-47FC-970E-F00D99CDBAB3",
      "token" : "0x6000067",
      "native_offset" : "0x0",
      "filename" : "MonoDevelop.MSBuildBuilder.exe",
      "sizeofimage" : "0x18000",
      "timestamp" : "0xc077b0d4",
      "il_offset" : "0x00001"
   }
,
  {
      "is_managed" : "true",
      "guid" : "E5BBCD86-B476-47FC-970E-F00D99CDBAB3",
      "token" : "0x6000075",
      "native_offset" : "0x0",
      "filename" : "MonoDevelop.MSBuildBuilder.exe",
      "sizeofimage" : "0x18000",
      "timestamp" : "0xc077b0d4",
      "il_offset" : "0x00057"
   }
,
  {
      "is_managed" : "true",
      "guid" : "E5BBCD86-B476-47FC-970E-F00D99CDBAB3",
      "token" : "0x00000",
      "native_offset" : "0x0",
      "filename" : "MonoDevelop.MSBuildBuilder.exe",
      "sizeofimage" : "0x18000",
      "timestamp" : "0xc077b0d4",
      "il_offset" : "0x0002a"
   }
,
  {
      "is_managed" : "false",
      "native_address" : "unregistered"
   }
,
  {
      "is_managed" : "true",
      "guid" : "55ADAE45-46CD-485B-A70E-2948332EBE8C",
      "token" : "0x00000",
      "native_offset" : "0x0",
      "filename" : "mscorlib.dll",
      "sizeofimage" : "0x474000",
      "timestamp" : "0xcdf122ed",
      "il_offset" : "0x0000c"
   }
,
  {
      "is_managed" : "true",
      "guid" : "55ADAE45-46CD-485B-A70E-2948332EBE8C",
      "token" : "0x6004ced",
      "native_offset" : "0x0",
      "filename" : "mscorlib.dll",
      "sizeofimage" : "0x474000",
      "timestamp" : "0xcdf122ed",
      "il_offset" : "0x0006a"
   }
,
  {
      "is_managed" : "true",
      "guid" : "55ADAE45-46CD-485B-A70E-2948332EBE8C",
      "token" : "0x60048d1",
      "native_offset" : "0x0",
      "filename" : "mscorlib.dll",
      "sizeofimage" : "0x474000",
      "timestamp" : "0xcdf122ed",
      "il_offset" : "0x00000"
   }
,
  {
      "is_managed" : "true",
      "guid" : "E5BBCD86-B476-47FC-970E-F00D99CDBAB3",
      "token" : "0x6000039",
      "native_offset" : "0x0",
      "filename" : "MonoDevelop.MSBuildBuilder.exe",
      "sizeofimage" : "0x18000",
      "timestamp" : "0xc077b0d4",
      "il_offset" : "0x00019"
   }
,
  {
      "is_managed" : "true",
      "guid" : "E5BBCD86-B476-47FC-970E-F00D99CDBAB3",
      "token" : "0x6000169",
      "native_offset" : "0x0",
      "filename" : "MonoDevelop.MSBuildBuilder.exe",
      "sizeofimage" : "0x18000",
      "timestamp" : "0xc077b0d4",
      "il_offset" : "0x00029"
   }
,
  {
      "is_managed" : "true",
      "guid" : "E5BBCD86-B476-47FC-970E-F00D99CDBAB3",
      "token" : "0x6000184",
      "native_offset" : "0x0",
      "filename" : "MonoDevelop.MSBuildBuilder.exe",
      "sizeofimage" : "0x18000",
      "timestamp" : "0xc077b0d4",
      "il_offset" : "0x00001"
   }
,
  {
      "is_managed" : "true",
      "guid" : "55ADAE45-46CD-485B-A70E-2948332EBE8C",
      "token" : "0x6001ff3",
      "native_offset" : "0x0",
      "filename" : "mscorlib.dll",
      "sizeofimage" : "0x474000",
      "timestamp" : "0xcdf122ed",
      "il_offset" : "0x00007"
   }
,
  {
      "is_managed" : "true",
      "guid" : "55ADAE45-46CD-485B-A70E-2948332EBE8C",
      "token" : "0x6001ece",
      "native_offset" : "0x0",
      "filename" : "mscorlib.dll",
      "sizeofimage" : "0x474000",
      "timestamp" : "0xcdf122ed",
      "il_offset" : "0x00071"
   }
,
  {
      "is_managed" : "true",
      "guid" : "55ADAE45-46CD-485B-A70E-2948332EBE8C",
      "token" : "0x6001ecc",
      "native_offset" : "0x0",
      "filename" : "mscorlib.dll",
      "sizeofimage" : "0x474000",
      "timestamp" : "0xcdf122ed",
      "il_offset" : "0x00000"
   }
,
  {
      "is_managed" : "true",
      "guid" : "55ADAE45-46CD-485B-A70E-2948332EBE8C",
      "token" : "0x6001ff1",
      "native_offset" : "0x0",
      "filename" : "mscorlib.dll",
      "sizeofimage" : "0x474000",
      "timestamp" : "0xcdf122ed",
      "il_offset" : "0x00021"
   }
,
  {
      "is_managed" : "true",
      "guid" : "55ADAE45-46CD-485B-A70E-2948332EBE8C",
      "token" : "0x6001fd9",
      "native_offset" : "0x0",
      "filename" : "mscorlib.dll",
      "sizeofimage" : "0x474000",
      "timestamp" : "0xcdf122ed",
      "il_offset" : "0x00074"
   }
,
  {
      "is_managed" : "true",
      "guid" : "55ADAE45-46CD-485B-A70E-2948332EBE8C",
      "token" : "0x6001fee",
      "native_offset" : "0x0",
      "filename" : "mscorlib.dll",
      "sizeofimage" : "0x474000",
      "timestamp" : "0xcdf122ed",
      "il_offset" : "0x00000"
   }
,
  {
      "is_managed" : "true",
      "guid" : "55ADAE45-46CD-485B-A70E-2948332EBE8C",
      "token" : "0x00000",
      "native_offset" : "0x0",
      "filename" : "mscorlib.dll",
      "sizeofimage" : "0x474000",
      "timestamp" : "0xcdf122ed",
      "il_offset" : "0x0002a"
   }

  ],
  "unmanaged_frames" : [
 {
    "is_managed" : "false",
    "native_address" : "0x106885346",
    "native_offset" : "0x00000"
  }
,
 {
    "is_managed" : "false",
    "native_address" : "0x106a1faa5",
    "native_offset" : "0x00000"
  }
,
 {
    "is_managed" : "false",
    "native_address" : "0x106a2011a",
    "native_offset" : "0x00000"
  }
,
 {
    "is_managed" : "false",
    "native_address" : "0x1068f1da7",
    "native_offset" : "0x00000"
  }
,
 {
    "is_managed" : "false",
    "native_address" : "0x106889fb5",
    "native_offset" : "0x00000"
  }
,
 {
    "is_managed" : "false",
    "native_address" : "0x1068f109f",
    "native_offset" : "0x00000"
  }
,
 {
    "is_managed" : "false",
    "native_address" : "0x7fff68c9a5fd",
    "native_offset" : "0x00000"
  }
,
 {
    "is_managed" : "false",
    "native_address" : "unregistered"
  }
,
 {
    "is_managed" : "false",
    "native_address" : "0x7fff68b70808",
    "native_offset" : "0x00000"
  }
,
 {
    "is_managed" : "false",
    "native_address" : "0x106aef397",
    "native_offset" : "0x00000"
  }
,
 {
    "is_managed" : "false",
    "native_address" : "0x106ad027f",
    "native_offset" : "0x00000"
  }
,
 {
    "is_managed" : "false",
    "native_address" : "0x106aef71e",
    "native_offset" : "0x00000"
  }
,
 {
    "is_managed" : "false",
    "native_address" : "0x106aef89f",
    "native_offset" : "0x00000"
  }
,
 {
    "is_managed" : "false",
    "native_address" : "0x10698c059",
    "native_offset" : "0x00000"
  }
,
 {
    "is_managed" : "false",
    "native_address" : "0x10698c5f2",
    "native_offset" : "0x00000"
  }
,
 {
    "is_managed" : "false",
    "native_address" : "0x106add6d1",
    "native_offset" : "0x00000"
  }
,
 {
    "is_managed" : "false",
    "native_address" : "0x106adda70",
    "native_offset" : "0x00000"
  }
,
 {
    "is_managed" : "false",
    "native_address" : "0x10698e706",
    "native_offset" : "0x00000"
  }
,
 {
    "is_managed" : "false",
    "native_address" : "0x1069b2ab4",
    "native_offset" : "0x00000"
  }
,
 {
    "is_managed" : "true",
    "guid" : "55ADAE45-46CD-485B-A70E-2948332EBE8C",
    "token" : "0x00000",
    "native_offset" : "0x0",
    "filename" : "mscorlib.dll",
    "sizeofimage" : "0x474000",
    "timestamp" : "0xcdf122ed",
    "il_offset" : "0x00000"
  }
,
 {
    "is_managed" : "true",
    "guid" : "55ADAE45-46CD-485B-A70E-2948332EBE8C",
    "token" : "0x6001f8c",
    "native_offset" : "0x0",
    "filename" : "mscorlib.dll",
    "sizeofimage" : "0x474000",
    "timestamp" : "0xcdf122ed",
    "il_offset" : "0x00000"
  }
,
 {
    "is_managed" : "true",
    "guid" : "E5BBCD86-B476-47FC-970E-F00D99CDBAB3",
    "token" : "0x6000083",
    "native_offset" : "0x0",
    "filename" : "MonoDevelop.MSBuildBuilder.exe",
    "sizeofimage" : "0x18000",
    "timestamp" : "0xc077b0d4",
    "il_offset" : "0x00000"
  }
,
 {
    "is_managed" : "true",
    "guid" : "E5BBCD86-B476-47FC-970E-F00D99CDBAB3",
    "token" : "0x600006a",
    "native_offset" : "0x0",
    "filename" : "MonoDevelop.MSBuildBuilder.exe",
    "sizeofimage" : "0x18000",
    "timestamp" : "0xc077b0d4",
    "il_offset" : "0x00000"
  }
,
 {
    "is_managed" : "true",
    "guid" : "E5BBCD86-B476-47FC-970E-F00D99CDBAB3",
    "token" : "0x60000a1",
    "native_offset" : "0x0",
    "filename" : "MonoDevelop.MSBuildBuilder.exe",
    "sizeofimage" : "0x18000",
    "timestamp" : "0xc077b0d4",
    "il_offset" : "0x00000"
  }
,
 {
    "is_managed" : "true",
    "guid" : "E5BBCD86-B476-47FC-970E-F00D99CDBAB3",
    "token" : "0x6000067",
    "native_offset" : "0x0",
    "filename" : "MonoDevelop.MSBuildBuilder.exe",
    "sizeofimage" : "0x18000",
    "timestamp" : "0xc077b0d4",
    "il_offset" : "0x00000"
  }
,
 {
    "is_managed" : "true",
    "guid" : "E5BBCD86-B476-47FC-970E-F00D99CDBAB3",
    "token" : "0x6000075",
    "native_offset" : "0x0",
    "filename" : "MonoDevelop.MSBuildBuilder.exe",
    "sizeofimage" : "0x18000",
    "timestamp" : "0xc077b0d4",
    "il_offset" : "0x00000"
  }
,
 {
    "is_managed" : "true",
    "guid" : "E5BBCD86-B476-47FC-970E-F00D99CDBAB3",
    "token" : "0x00000",
    "native_offset" : "0x0",
    "filename" : "MonoDevelop.MSBuildBuilder.exe",
    "sizeofimage" : "0x18000",
    "timestamp" : "0xc077b0d4",
    "il_offset" : "0x00000"
  }
,
 {
    "is_managed" : "false",
    "native_address" : "0x1067e7ae2",
    "native_offset" : "0x00000"
  }
,
 {
    "is_managed" : "false",
    "native_address" : "0x1069f5967",
    "native_offset" : "0x00000"
  }
,
 {
    "is_managed" : "false",
    "native_address" : "0x1069fe409",
    "native_offset" : "0x00000"
  }
,
 {
    "is_managed" : "false",
    "native_address" : "0x10699638d",
    "native_offset" : "0x00000"
  }
,
 {
    "is_managed" : "false",
    "native_address" : "0x1069aa027",
    "native_offset" : "0x00000"
  }
,
 {
    "is_managed" : "true",
    "guid" : "55ADAE45-46CD-485B-A70E-2948332EBE8C",
    "token" : "0x00000",
    "native_offset" : "0x0",
    "filename" : "mscorlib.dll",
    "sizeofimage" : "0x474000",
    "timestamp" : "0xcdf122ed",
    "il_offset" : "0x00000"
  }
,
 {
    "is_managed" : "true",
    "guid" : "55ADAE45-46CD-485B-A70E-2948332EBE8C",
    "token" : "0x6004ced",
    "native_offset" : "0x0",
    "filename" : "mscorlib.dll",
    "sizeofimage" : "0x474000",
    "timestamp" : "0xcdf122ed",
    "il_offset" : "0x00000"
  }
,
 {
    "is_managed" : "true",
    "guid" : "55ADAE45-46CD-485B-A70E-2948332EBE8C",
    "token" : "0x60048d1",
    "native_offset" : "0x0",
    "filename" : "mscorlib.dll",
    "sizeofimage" : "0x474000",
    "timestamp" : "0xcdf122ed",
    "il_offset" : "0x00000"
  }
,
 {
    "is_managed" : "true",
    "guid" : "E5BBCD86-B476-47FC-970E-F00D99CDBAB3",
    "token" : "0x6000169",
    "native_offset" : "0x0",
    "filename" : "MonoDevelop.MSBuildBuilder.exe",
    "sizeofimage" : "0x18000",
    "timestamp" : "0xc077b0d4",
    "il_offset" : "0x00000"
  }
,
 {
    "is_managed" : "true",
    "guid" : "E5BBCD86-B476-47FC-970E-F00D99CDBAB3",
    "token" : "0x6000184",
    "native_offset" : "0x0",
    "filename" : "MonoDevelop.MSBuildBuilder.exe",
    "sizeofimage" : "0x18000",
    "timestamp" : "0xc077b0d4",
    "il_offset" : "0x00000"
  }
,
 {
    "is_managed" : "true",
    "guid" : "55ADAE45-46CD-485B-A70E-2948332EBE8C",
    "token" : "0x6001ff3",
    "native_offset" : "0x0",
    "filename" : "mscorlib.dll",
    "sizeofimage" : "0x474000",
    "timestamp" : "0xcdf122ed",
    "il_offset" : "0x00000"
  }
,
 {
    "is_managed" : "true",
    "guid" : "55ADAE45-46CD-485B-A70E-2948332EBE8C",
    "token" : "0x6001ecc",
    "native_offset" : "0x0",
    "filename" : "mscorlib.dll",
    "sizeofimage" : "0x474000",
    "timestamp" : "0xcdf122ed",
    "il_offset" : "0x00000"
  }
,
 {
    "is_managed" : "true",
    "guid" : "55ADAE45-46CD-485B-A70E-2948332EBE8C",
    "token" : "0x6001fee",
    "native_offset" : "0x0",
    "filename" : "mscorlib.dll",
    "sizeofimage" : "0x474000",
    "timestamp" : "0xcdf122ed",
    "il_offset" : "0x00000"
  }
,
 {
    "is_managed" : "false",
    "native_address" : "0x1067e7ae2",
    "native_offset" : "0x00000"
  }
,
 {
    "is_managed" : "false",
    "native_address" : "0x1069f7342",
    "native_offset" : "0x00000"
  }
,
 {
    "is_managed" : "false",
    "native_address" : "0x106a231c7",
    "native_offset" : "0x00000"
  }
,
 {
    "is_managed" : "false",
    "native_address" : "0x106956f88",
    "native_offset" : "0x00000"
  }
,
 {
    "is_managed" : "false",
    "native_address" : "0x106a206ed",
    "native_offset" : "0x00000"
  }
,
 {
    "is_managed" : "false",
    "native_address" : "0x7fff68ca6109",
    "native_offset" : "0x00000"
  }
,
 {
    "is_managed" : "false",
    "native_address" : "0x7fff68ca1b8b",
    "native_offset" : "0x00000"
  }

 ]
},
{
  "is_managed" : false,
  "offset_free_hash" : "0x0",
  "offset_rich_hash" : "0x0",
  "crashed" : false,
  "native_thread_id" : "0x107c20dc0",
  "thread_info_addr" : "0x7fe0b6808200",
  "thread_name" : "tid_307",
  "ctx" : {
    "IP" : "0x7fff68be5882",
    "SP" : "0x7ffee942aca8",
    "BP" : "0x7ffee942ad40"
 },
  "unmanaged_frames" : [
 {
    "is_managed" : "false",
    "native_address" : "0x106885346",
    "native_offset" : "0x00000"
  }
,
 {
    "is_managed" : "false",
    "native_address" : "0x106a1faa5",
    "native_offset" : "0x00000"
  }
,
 {
    "is_managed" : "false",
    "native_address" : "0x106a1f7d7",
    "native_offset" : "0x00000"
  }
,
 {
    "is_managed" : "false",
    "native_address" : "0x1068f0ce0",
    "native_offset" : "0x00000"
  }
,
 {
    "is_managed" : "false",
    "native_address" : "0x7fff68c9a5fd",
    "native_offset" : "0x00000"
  }
,
 {
    "is_managed" : "false",
    "native_address" : "0x7ffee942a998",
    "native_offset" : "0x00000"
  }
,
 {
    "is_managed" : "false",
    "native_address" : "0x106acc430",
    "native_offset" : "0x00000"
  }
,
 {
    "is_managed" : "false",
    "native_address" : "0x106ae4401",
    "native_offset" : "0x00000"
  }
,
 {
    "is_managed" : "false",
    "native_address" : "0x106a1c9e4",
    "native_offset" : "0x00000"
  }
,
 {
    "is_managed" : "false",
    "native_address" : "0x106a1c7ea",
    "native_offset" : "0x00000"
  }
,
 {
    "is_managed" : "false",
    "native_address" : "0x10684b30a",
    "native_offset" : "0x00000"
  }
,
 {
    "is_managed" : "false",
    "native_address" : "0x1067d6e49",
    "native_offset" : "0x00000"
  }
,
 {
    "is_managed" : "false",
    "native_address" : "0x7fff68aa1cc9",
    "native_offset" : "0x00000"
  }

 ]
},
{
  "is_managed" : false,
  "offset_free_hash" : "0xb38e38cc",
  "offset_rich_hash" : "0xb38e38cc",
  "crashed" : false,
  "native_thread_id" : "0x700003610000",
  "thread_info_addr" : "0x7fe0b5015c00",
  "thread_name" : "Finalizer",
  "ctx" : {
    "IP" : "0x7fff68be2e36",
    "SP" : "0x70000360feb8",
    "BP" : "0x70000360ff00"
 },
  "unmanaged_frames" : [
 {
    "is_managed" : "false",
    "native_address" : "0x106885346",
    "native_offset" : "0x00000"
  }
,
 {
    "is_managed" : "false",
    "native_address" : "0x106a1faa5",
    "native_offset" : "0x00000"
  }
,
 {
    "is_managed" : "false",
    "native_address" : "0x106a1f7d7",
    "native_offset" : "0x00000"
  }
,
 {
    "is_managed" : "false",
    "native_address" : "0x1068f0ce0",
    "native_offset" : "0x00000"
  }
,
 {
    "is_managed" : "false",
    "native_address" : "0x7fff68c9a5fd",
    "native_offset" : "0x00000"
  }
,
 {
    "is_managed" : "true",
    "guid" : "55ADAE45-46CD-485B-A70E-2948332EBE8C",
    "token" : "0x6001467",
    "native_offset" : "0x0",
    "filename" : "mscorlib.dll",
    "sizeofimage" : "0x474000",
    "timestamp" : "0xcdf122ed",
    "il_offset" : "0x00000"
  }
,
 {
    "is_managed" : "false",
    "native_address" : "0x106a206ed",
    "native_offset" : "0x00000"
  }
,
 {
    "is_managed" : "false",
    "native_address" : "0x7fff68ca6109",
    "native_offset" : "0x00000"
  }
,
 {
    "is_managed" : "false",
    "native_address" : "0x7fff68ca1b8b",
    "native_offset" : "0x00000"
  }

 ]
}
]
}